[
  {
    "id": 1,
    "size": 44,
    "purpose": "Performance",
    "isFunctional": true,
    "wheelHardness": 36,
    "hourlyFee": 3
  },
  {
    "id": 2,
    "size": 46,
    "purpose": "Figure",
    "isFunctional": false,
    "wheelHardness": 75,
    "hourlyFee": 2
  },
  {
    "id": 3,
    "size": 47,
    "purpose": "Figure",
    "isFunctional": true,
    "wheelHardness": 10,
    "hourlyFee": 4
  },
  {
    "id": 14,
    "size": 42,
    "purpose": "Figure",
    "isFunctional": false,
    "wheelHardness": 91,
    "hourlyFee": 5
  },
  {
    "id": 20,
    "size": 43,
    "purpose": "Hockey",
    "isFunctional": true,
    "wheelHardness": 89,
    "hourlyFee": 2
  }
]